SemiFlow/Model.py
SemiFlow/__init__.py
SemiFlow/activations.py
SemiFlow/initializers.py
SemiFlow/losses.py
SemiFlow/optimizers.py
SemiFlow/engine/GradientDescentOptimizer.py
SemiFlow/engine/__init__.py
SemiFlow/engine/activations.py
SemiFlow/engine/core.py
SemiFlow/engine/graph.py
SemiFlow/engine/losses.py
SemiFlow/engine/node.py
SemiFlow/engine/operations.py
SemiFlow/engine/placeholder.py
SemiFlow/engine/session.py
SemiFlow/engine/utils.py
SemiFlow/engine/variable.py
SemiFlow/layer/__init__.py
SemiFlow/layer/convolutional.py
SemiFlow/layer/core.py
SemiFlow/layer/dense.py
SemiFlow/layer/input.py
SemiFlow/layer/pooling.py
SemiFlow/layer/reshape.py
SemiFlow/layer/rnn.py
SemiFlow/utils/__init__.py
SemiFlow/utils/convert.py
SemiFlow/utils/data_utils.py
SemiFlow/utils/dataset.py
SemiFlow/utils/download.py
SemiFlow/utils/history.py
SemiFlow/utils/distributed_tools/__init__.py
SemiFlow/utils/distributed_tools/client.py
SemiFlow/utils/distributed_tools/message.py
SemiFlow/utils/distributed_tools/server.py
SemiFlow-1.1.3.dist-info/LICENSE.txt
SemiFlow-1.1.3.dist-info/METADATA
SemiFlow-1.1.3.dist-info/WHEEL
SemiFlow-1.1.3.dist-info/top_level.txt
SemiFlow-1.1.3.dist-info/RECORD
