Metadata-Version: 2.1
Name: SemiFlow
Version: 1.1.3
Summary: SemiFlow is a deep learning framework with automatic differentiation and automatic shape inference, developing from Numpy.
Home-page: https://github.com/nanguoyu/SemiFlow
Author: Dong Wang (nanguoyu)
Author-email: dongwang@wangdongdong.wang
Maintainer: Dong Wang (nanguoyu)
Maintainer-email: dongwang@wangdongdong.wang
Requires-Python: >=3.8
License-File: LICENSE.txt
Requires-Dist: numpy
Requires-Dist: matplotlib
Requires-Dist: onnx
